xdeep/__init__.py
xdeep/utils/__init__.py
xdeep/utils/imagenet.py
xdeep/utils/resources/__init__.py
xdeep/xglobal/__init__.py
xdeep/xglobal/global_explainers.py
xdeep/xglobal/methods/__init__.py
xdeep/xglobal/methods/activation.py
xdeep/xglobal/methods/inverted_representation.py
xdeep/xlocal/__init__.py
xdeep/xlocal/gradient/__init__.py
xdeep/xlocal/gradient/explainers.py
xdeep/xlocal/gradient/backprop/__init__.py
xdeep/xlocal/gradient/backprop/base.py
xdeep/xlocal/gradient/backprop/guided_backprop.py
xdeep/xlocal/gradient/backprop/integrate_grad.py
xdeep/xlocal/gradient/backprop/smooth_grad.py
xdeep/xlocal/gradient/cam/__init__.py
xdeep/xlocal/gradient/cam/basecam.py
xdeep/xlocal/gradient/cam/gradcam.py
xdeep/xlocal/gradient/cam/gradcampp.py
xdeep/xlocal/gradient/cam/scorecam.py
xdeep/xlocal/perturbation/__init__.py
xdeep/xlocal/perturbation/exceptions.py
xdeep/xlocal/perturbation/explainer.py
xdeep/xlocal/perturbation/xdeep_base.py
xdeep/xlocal/perturbation/xdeep_image.py
xdeep/xlocal/perturbation/xdeep_tabular.py
xdeep/xlocal/perturbation/xdeep_text.py
xdeep/xlocal/perturbation/cle/__init__.py
xdeep/xlocal/perturbation/cle/cle_image.py
xdeep/xlocal/perturbation/cle/cle_tabular.py
xdeep/xlocal/perturbation/cle/cle_text.py
xdeep/xlocal/perturbation/image_explainers/__init__.py
xdeep/xlocal/perturbation/image_explainers/anchor_image.py
xdeep/xlocal/perturbation/image_explainers/cle_image.py
xdeep/xlocal/perturbation/image_explainers/lime_image.py
xdeep/xlocal/perturbation/image_explainers/shap_image.py
xdeep/xlocal/perturbation/tabular_explainers/__init__.py
xdeep/xlocal/perturbation/tabular_explainers/anchor_tabular.py
xdeep/xlocal/perturbation/tabular_explainers/cle_tabular.py
xdeep/xlocal/perturbation/tabular_explainers/lime_tabular.py
xdeep/xlocal/perturbation/tabular_explainers/shap_tabular.py
xdeep/xlocal/perturbation/text_explainers/__init__.py
xdeep/xlocal/perturbation/text_explainers/anchor_text.py
xdeep/xlocal/perturbation/text_explainers/cle_text.py
x_deep-0.0.9.dist-info/LICENSE
x_deep-0.0.9.dist-info/METADATA
x_deep-0.0.9.dist-info/WHEEL
x_deep-0.0.9.dist-info/top_level.txt
x_deep-0.0.9.dist-info/RECORD
