Metadata-Version: 2.1
Name: x-deep
Version: 0.0.9
Summary: XDeep is an open-source package for Interpretable Machine Learning.
Home-page: https://github.com/datamllab/xdeep
Author: DATA LAB at Texas A&M University
Author-email: hu@cse.tamu.edu
License: UNKNOWN
Platform: UNKNOWN
Classifier: Programming Language :: Python :: 3.6
Classifier: License :: OSI Approved :: MIT License
Classifier: Operating System :: OS Independent
Requires-Dist: anchor-exp
Requires-Dist: shap
Requires-Dist: torch
Requires-Dist: torchvision
